smartapi_login/__init__.py
smartapi_login/main.py
smartapi_login-1.0.0.7.dist-info/LICENSE
smartapi_login-1.0.0.7.dist-info/METADATA
smartapi_login-1.0.0.7.dist-info/WHEEL
smartapi_login-1.0.0.7.dist-info/entry_points.txt
smartapi_login-1.0.0.7.dist-info/top_level.txt
smartapi_login-1.0.0.7.dist-info/RECORD
