Metadata-Version: 2.1
Name: smartapi_login
Version: 1.0.0.7
Summary: A library for interacting with SmartAPI for historical data, trading sessions, and more.
Home-page: https://github.com/maheshrajbhar90/smartapi-login.git
Author: Mahesh Kumar
Author-email: maheshrajbhar90@gmail.com
Classifier: Programming Language :: Python :: 3
Classifier: License :: OSI Approved :: MIT License
Classifier: Operating System :: OS Independent
Requires-Python: >=3.6
License-File: LICENSE
Requires-Dist: pandas>=1.0.0
Requires-Dist: requests>=2.0.0
Requires-Dist: pytz>=2020.1
Requires-Dist: pyotp>=2.0.0
